libname/__init__.py
libname/argument.py
libname/utils.py
libname/verilog.py
libname/config/__init__.py
libname/config/config.py
libname/config/path.py
morell_test_attempt_verilog-0.0.2.dist-info/LICENSE
morell_test_attempt_verilog-0.0.2.dist-info/METADATA
morell_test_attempt_verilog-0.0.2.dist-info/WHEEL
morell_test_attempt_verilog-0.0.2.dist-info/top_level.txt
morell_test_attempt_verilog-0.0.2.dist-info/RECORD
