Metadata-Version: 2.1
Name: morell-test-attempt-verilog
Version: 0.0.2
Summary: A Verilog Class
Home-page: UNKNOWN
Author: Morteza Rezaalipour (MorellRAP)
Author-email: <rezaalipour.usi@gmail.com>
License: UNKNOWN
Keywords: python,verilog,circuits,synthesis
Platform: UNKNOWN
Classifier: Development Status :: 1 - Planning
Classifier: Intended Audience :: Developers
Classifier: Programming Language :: Python :: 3
Classifier: Operating System :: Unix
Classifier: Operating System :: MacOS :: MacOS X
Classifier: Operating System :: Microsoft :: Windows
License-File: LICENSE
Requires-Dist: numpy
Requires-Dist: scipy
Requires-Dist: pandas
Requires-Dist: matplotlib
Requires-Dist: networkx
Requires-Dist: python-dateutil
Requires-Dist: PyYAML
